{
  "type": "forge:conditional",
  "recipes": [
    {
      "conditions": [
        {
          "type": "woodworks:config",
          "value": "wooden_bookshelves"
        }
      ],
      "recipe": {
        "type": "minecraft:crafting_shaped",
        "category": "building",
        "key": {
          "#": {
            "item": "minecraft:crimson_planks"
          },
          "X": {
            "item": "minecraft:crimson_slab"
          }
        },
        "pattern": [
          "###",
          "XXX",
          "###"
        ],
        "result": {
          "item": "woodworks:chiseled_crimson_bookshelf"
        },
        "show_notification": true
      }
    }
  ]
}